{
  "ud0e39lcl4iti8439lcl4iti842": [
    {
      "name": "rani",
      "passportID": "77522",
      "cash": 16000,
      "credit": 21000,
      "accounts": ["90sl4iw0fy5"],
      "accountsAccess": ["f84l4ivy3f3"]
    },
    {
      "name": "tofik",
      "passportID": "775223553",
      "cash": 54000,
      "credit": 10000,
      "accounts": ["f84l4ivy3f3", "f4gl4ivyp8e"],
      "accountsAccess": []
    },
    {
      "name": "rafael",
      "passportID": "235532155",
      "cash": 99000,
      "credit": 2000,
      "accounts": ["6xgl4k5ekd6"],
      "accountsAccess": []
    }
  ],
  "ud0e3628l4iup0cc628l4iup0cb": [],
  "ud0e3700l4iupkhg700l4iupkhf": [],
  "ud0e37g8l4iupxdh7g8l4iupxdg": []
}
